apify_scrapy_executor/__init__.py
apify_scrapy_executor/apify_scrapy_executor.py
apify_scrapy_executor-0.0.10.dist-info/LICENSE
apify_scrapy_executor-0.0.10.dist-info/METADATA
apify_scrapy_executor-0.0.10.dist-info/WHEEL
apify_scrapy_executor-0.0.10.dist-info/top_level.txt
apify_scrapy_executor-0.0.10.dist-info/RECORD
