Metadata-Version: 2.1
Name: apify-scrapy-executor
Version: 0.0.10
Summary: Executes migrated scrapy project to Apify platform
Home-page: https://github.com/spiduso/apify-scrapy-executor
Author: Hoang Anh Tuan
Author-email: hoang.dusan@gmail.com
Project-URL: Bug Tracker, https://github.com/spiduso/apify-scrapy-executor/issues
Classifier: Programming Language :: Python :: 3
Classifier: Operating System :: OS Independent
Requires-Python: >=3.9
License-File: LICENSE
